README.txt
setup.cfg
setup.py
tweeql2solr/__init__.py
tweeql2solr/config.py
tweeql2solr/functions.py
tweeql2solr/patch.py
tweeql2solr/scripts.py
tweeql2solr/tests.py
tweeql2solr.egg-info/PKG-INFO
tweeql2solr.egg-info/SOURCES.txt
tweeql2solr.egg-info/dependency_links.txt
tweeql2solr.egg-info/entry_points.txt
tweeql2solr.egg-info/not-zip-safe
tweeql2solr.egg-info/requires.txt
tweeql2solr.egg-info/top_level.txt