Metadata-Version: 1.0
Name: tweeql2solr
Version: 0.1
Summary: tweeql2solr - store tweets in solr
Home-page: https://github.com/gawel/tweeql2solr
Author: Bearstech
Author-email: gpasgrimaud@bearstech.com
License: BSD
Platform: UNKNOWN
Classifier: Intended Audience :: Developers
Classifier: License :: OSI Approved :: BSD License
Classifier: Operating System :: OS Independent
Classifier: Programming Language :: Python
Classifier: Topic :: Internet :: WWW/HTTP :: Indexing/Search
